LICENSE
MANIFEST.in
PILOTVERSION
README.md
pilot.py
setup.cfg
setup.py
panda_pilot.egg-info/PKG-INFO
panda_pilot.egg-info/SOURCES.txt
panda_pilot.egg-info/dependency_links.txt
panda_pilot.egg-info/top_level.txt
pilot/__init__.py
pilot/api/__init__.py
pilot/api/analytics.py
pilot/api/benchmark.py
pilot/api/data.py
pilot/api/es_data.py
pilot/api/memorymonitor.py
pilot/api/services.py
pilot/common/__init__.py
pilot/common/errorcodes.py
pilot/common/exception.py
pilot/common/pluginfactory.py
pilot/control/__init__.py
pilot/control/data.py
pilot/control/interceptor.py
pilot/control/job.py
pilot/control/monitor.py
pilot/control/payload.py
pilot/control/payloads/__init__.py
pilot/control/payloads/eventservice.py
pilot/control/payloads/eventservicemerge.py
pilot/control/payloads/generic.py
pilot/copytool/__init__.py
pilot/copytool/common.py
pilot/copytool/gfal.py
pilot/copytool/gs.py
pilot/copytool/lsm.py
pilot/copytool/mv.py
pilot/copytool/objectstore.py
pilot/copytool/rucio.py
pilot/copytool/s3.py
pilot/copytool/xrdcp.py
pilot/eventservice/__init__.py
pilot/eventservice/droid.py
pilot/eventservice/yoda.py
pilot/eventservice/communicationmanager/__init__.py
pilot/eventservice/communicationmanager/communicationmanager.py
pilot/eventservice/communicationmanager/plugins/__init__.py
pilot/eventservice/communicationmanager/plugins/basecommunicator.py
pilot/eventservice/communicationmanager/plugins/pandacommunicator.py
pilot/eventservice/esprocess/__init__.py
pilot/eventservice/esprocess/eshook.py
pilot/eventservice/esprocess/esmanager.py
pilot/eventservice/esprocess/esmessage.py
pilot/eventservice/esprocess/esprocess.py
pilot/eventservice/esprocess/hooks/__init__.py
pilot/eventservice/esprocess/hooks/acthook.py
pilot/eventservice/esprocess/hooks/harvesterhook.py
pilot/eventservice/workexecutor/__init__.py
pilot/eventservice/workexecutor/workexecutor.py
pilot/eventservice/workexecutor/plugins/__init__.py
pilot/eventservice/workexecutor/plugins/baseexecutor.py
pilot/eventservice/workexecutor/plugins/genericexecutor.py
pilot/eventservice/workexecutor/plugins/hpoexecutor.py
