Metadata-Version: 2.1
Name: panda-pilot
Version: 3.7.0.36
Summary: PanDA Pilot 3
Home-page: https://github.com/PanDAWMS/pilot3/wiki
Author: PanDA Team
Author-email: atlas-adc-panda@cern.ch
License: Apache License 2.0
Requires-Python: >=3.6
License-File: LICENSE
